universal_mcp_outlook/README.md
universal_mcp_outlook/__init__.py
universal_mcp_outlook/app.py
universal_mcp_outlook/server.py
universal_mcp_outlook-0.1.15.dist-info/METADATA
universal_mcp_outlook-0.1.15.dist-info/WHEEL
universal_mcp_outlook-0.1.15.dist-info/entry_points.txt
universal_mcp_outlook-0.1.15.dist-info/licenses/LICENSE
universal_mcp_outlook-0.1.15.dist-info/RECORD
